number_line.py
number_line-0.0.1.dist-info/metadata.json
number_line-0.0.1.dist-info/WHEEL
number_line-0.0.1.dist-info/METADATA
number_line-0.0.1.dist-info/DESCRIPTION.rst
number_line-0.0.1.dist-info/top_level.txt
number_line-0.0.1.dist-info/RECORD
