Metadata-Version: 2.0
Name: number-line
Version: 0.0.1
Summary: Package for creating a number line that contains different ranges and points
Home-page: https://bitbucket.org/liammccluskey/number_line.git
Author: Liam McCluskey
Author-email: lmm459@rutgers.edu
License: UNKNOWN
Platform: UNKNOWN
Classifier: Programming Language :: Python :: 3
Classifier: Programming Language :: Python :: 2.7
Classifier: License :: OSI Approved :: MIT License
Classifier: Operating System :: OS Independent
